CONTRIBUTING.md
MANIFEST.in
README.rst
setup.py
docs/HISTORY.txt
docs/LICENSE.GPL
docs/LICENSE.txt
eea/__init__.py
eea.cache.egg-info/PKG-INFO
eea.cache.egg-info/SOURCES.txt
eea.cache.egg-info/dependency_links.txt
eea.cache.egg-info/entry_points.txt
eea.cache.egg-info/namespace_packages.txt
eea.cache.egg-info/not-zip-safe
eea.cache.egg-info/requires.txt
eea.cache.egg-info/top_level.txt
eea/cache/README.txt
eea/cache/__init__.py
eea/cache/config.py
eea/cache/configure.zcml
eea/cache/event.py
eea/cache/interfaces.py
eea/cache/overrides.zcml
eea/cache/permissions.zcml
eea/cache/profiles.zcml
eea/cache/utility.py
eea/cache/version.txt
eea/cache/Extensions/install.py
eea/cache/browser/__init__.py
eea/cache/browser/configure.zcml
eea/cache/browser/interfaces.py
eea/cache/browser/app/__init__.py
eea/cache/browser/app/edit.py
eea/cache/browser/app/view.py
eea/cache/profiles/default/actions.xml
eea/cache/profiles/default/browserlayer.xml
eea/cache/profiles/default/metadata.xml
eea/cache/profiles/default/rolemap.xml
eea/cache/profiles/uninstall/actions.xml
eea/cache/profiles/uninstall/browserlayer.xml
eea/cache/profiles/uninstall/eea.cache.uninstall.txt
eea/cache/subtypes/__init__.py
eea/cache/subtypes/configure.zcml
eea/cache/subtypes/interfaces.py
eea/cache/tests/__init__.py
eea/cache/tests/base.py
eea/cache/tests/fake.py
eea/cache/tests/testDocTest.py